btnetutils/__init__.py
btnetutils/btnetutils.py
btnetutils/cli.py
btnetutils-0.1.0.dist-info/AUTHORS.rst
btnetutils-0.1.0.dist-info/LICENSE
btnetutils-0.1.0.dist-info/METADATA
btnetutils-0.1.0.dist-info/WHEEL
btnetutils-0.1.0.dist-info/entry_points.txt
btnetutils-0.1.0.dist-info/top_level.txt
btnetutils-0.1.0.dist-info/RECORD
